{
  "schema_version": "1.0",
  "generated_at": "2026-06-20T06:56:19.493Z",
  "source_layer": "change-events",
  "total": 57,
  "counts": {
    "improving": 23,
    "weakening": 5,
    "stable": 5,
    "deteriorating": 15,
    "leadership_gain": 5,
    "leadership_loss": 0,
    "confirmation_gain": 0,
    "confirmation_loss": 0,
    "regime_shift": 4,
    "narrative_shift": 0
  },
  "significant": [
    "a1602e3198a62b25",
    "53bb1c7e328ee58d",
    "6111d88aebb071d3",
    "e5e2d302e15ef208",
    "869aeecfb1a1bbec",
    "06d38a593dd6a9cb",
    "482f01845de7d385",
    "efbcafbfbe4647db",
    "853b3f33427fba25",
    "24f1af3e739bb1e4",
    "45492b27380ba5e3",
    "21477076823a5228"
  ],
  "events": [
    {
      "entity": "HYG",
      "entity_type": "etf",
      "slug": "hyg",
      "timestamp": "2026-06-20T06:05:13.910Z",
      "from_state": null,
      "to_state": "improving",
      "change_type": "improving",
      "confidence": "high",
      "source": "etf-history(window)",
      "href": "/research/etfs/hyg/",
      "research_href": "/research/etfs/hyg/",
      "evidence": [
        "intraseries window trend=accelerating band=high from HYG OHLCV",
        "current rank state=improving"
      ],
      "id": "24f1af3e739bb1e4",
      "label_en": "improving",
      "label_ar": "يتحسن",
      "confidence_en": "high",
      "confidence_ar": "عالية"
    },
    {
      "entity": "IEF",
      "entity_type": "etf",
      "slug": "ief",
      "timestamp": "2026-06-20T06:05:13.910Z",
      "from_state": null,
      "to_state": "improving",
      "change_type": "improving",
      "confidence": "high",
      "source": "etf-history(window)",
      "href": "/research/etfs/ief/",
      "research_href": "/research/etfs/ief/",
      "evidence": [
        "intraseries window trend=accelerating band=high from IEF OHLCV",
        "current rank state=improving"
      ],
      "id": "45492b27380ba5e3",
      "label_en": "improving",
      "label_ar": "يتحسن",
      "confidence_en": "high",
      "confidence_ar": "عالية"
    },
    {
      "entity": "LQD",
      "entity_type": "etf",
      "slug": "lqd",
      "timestamp": "2026-06-20T06:05:13.910Z",
      "from_state": null,
      "to_state": "improving",
      "change_type": "improving",
      "confidence": "high",
      "source": "etf-history(window)",
      "href": "/research/etfs/lqd/",
      "research_href": "/research/etfs/lqd/",
      "evidence": [
        "intraseries window trend=improving band=high from LQD OHLCV",
        "current rank state=improving"
      ],
      "id": "21477076823a5228",
      "label_en": "improving",
      "label_ar": "يتحسن",
      "confidence_en": "high",
      "confidence_ar": "عالية"
    },
    {
      "entity": "QQQ",
      "entity_type": "etf",
      "slug": "qqq",
      "timestamp": "2026-06-20T06:05:13.910Z",
      "from_state": null,
      "to_state": "improving",
      "change_type": "stable",
      "confidence": "high",
      "source": "etf-history(window)",
      "href": "/research/etfs/qqq/",
      "research_href": "/research/etfs/qqq/",
      "evidence": [
        "intraseries window trend=stable band=high from QQQ OHLCV",
        "current rank state=improving"
      ],
      "id": "56946b2bf5ba8093",
      "label_en": "stable",
      "label_ar": "مستقر",
      "confidence_en": "high",
      "confidence_ar": "عالية"
    },
    {
      "entity": "SCHD",
      "entity_type": "etf",
      "slug": "schd",
      "timestamp": "2026-06-20T06:05:13.910Z",
      "from_state": null,
      "to_state": "improving",
      "change_type": "weakening",
      "confidence": "high",
      "source": "etf-history(window)",
      "href": "/research/etfs/schd/",
      "research_href": "/research/etfs/schd/",
      "evidence": [
        "intraseries window trend=weakening band=high from SCHD OHLCV",
        "current rank state=improving"
      ],
      "id": "fe2a51a2a44d604e",
      "label_en": "weakening",
      "label_ar": "يضعف",
      "confidence_en": "high",
      "confidence_ar": "عالية"
    },
    {
      "entity": "SMH",
      "entity_type": "etf",
      "slug": "smh",
      "timestamp": "2026-06-20T06:05:13.910Z",
      "from_state": null,
      "to_state": "improving",
      "change_type": "improving",
      "confidence": "high",
      "source": "etf-history(window)",
      "href": "/research/etfs/smh/",
      "research_href": "/research/etfs/smh/",
      "evidence": [
        "intraseries window trend=improving band=high from SMH OHLCV",
        "current rank state=improving"
      ],
      "id": "06ac7c70dffd7038",
      "label_en": "improving",
      "label_ar": "يتحسن",
      "confidence_en": "high",
      "confidence_ar": "عالية"
    },
    {
      "entity": "SOXX",
      "entity_type": "etf",
      "slug": "soxx",
      "timestamp": "2026-06-20T06:05:13.910Z",
      "from_state": null,
      "to_state": "improving",
      "change_type": "improving",
      "confidence": "high",
      "source": "etf-history(window)",
      "href": "/research/etfs/soxx/",
      "research_href": "/research/etfs/soxx/",
      "evidence": [
        "intraseries window trend=improving band=high from SOXX OHLCV",
        "current rank state=improving"
      ],
      "id": "4103f0ded52ae81d",
      "label_en": "improving",
      "label_ar": "يتحسن",
      "confidence_en": "high",
      "confidence_ar": "عالية"
    },
    {
      "entity": "TLT",
      "entity_type": "etf",
      "slug": "tlt",
      "timestamp": "2026-06-20T06:05:13.910Z",
      "from_state": null,
      "to_state": "improving",
      "change_type": "improving",
      "confidence": "high",
      "source": "etf-history(window)",
      "href": "/research/etfs/tlt/",
      "research_href": "/research/etfs/tlt/",
      "evidence": [
        "intraseries window trend=accelerating band=high from TLT OHLCV",
        "current rank state=improving"
      ],
      "id": "b3138588ff0e13fb",
      "label_en": "improving",
      "label_ar": "يتحسن",
      "confidence_en": "high",
      "confidence_ar": "عالية"
    },
    {
      "entity": "VOO",
      "entity_type": "etf",
      "slug": "voo",
      "timestamp": "2026-06-20T06:05:13.910Z",
      "from_state": null,
      "to_state": "improving",
      "change_type": "deteriorating",
      "confidence": "high",
      "source": "etf-history(window)",
      "href": "/research/etfs/voo/",
      "research_href": "/research/etfs/voo/",
      "evidence": [
        "intraseries window trend=deteriorating band=high from VOO OHLCV",
        "current rank state=improving"
      ],
      "id": "bb4016d199812f28",
      "label_en": "deteriorating",
      "label_ar": "يتدهور",
      "confidence_en": "high",
      "confidence_ar": "عالية"
    },
    {
      "entity": "VTI",
      "entity_type": "etf",
      "slug": "vti",
      "timestamp": "2026-06-20T06:05:13.910Z",
      "from_state": null,
      "to_state": "improving",
      "change_type": "improving",
      "confidence": "high",
      "source": "etf-history(window)",
      "href": "/research/etfs/vti/",
      "research_href": "/research/etfs/vti/",
      "evidence": [
        "intraseries window trend=improving band=high from VTI OHLCV",
        "current rank state=improving"
      ],
      "id": "e64e15af018f9413",
      "label_en": "improving",
      "label_ar": "يتحسن",
      "confidence_en": "high",
      "confidence_ar": "عالية"
    },
    {
      "entity": "XLB",
      "entity_type": "etf",
      "slug": "xlb",
      "timestamp": "2026-06-20T06:05:13.910Z",
      "from_state": null,
      "to_state": "improving",
      "change_type": "improving",
      "confidence": "high",
      "source": "etf-history(window)",
      "href": "/research/etfs/xlb/",
      "research_href": "/research/etfs/xlb/",
      "evidence": [
        "intraseries window trend=improving band=high from XLB OHLCV",
        "current rank state=improving"
      ],
      "id": "0c5a4703e77e7ebb",
      "label_en": "improving",
      "label_ar": "يتحسن",
      "confidence_en": "high",
      "confidence_ar": "عالية"
    },
    {
      "entity": "XLE",
      "entity_type": "etf",
      "slug": "xle",
      "timestamp": "2026-06-20T06:05:13.910Z",
      "from_state": null,
      "to_state": "weakening",
      "change_type": "weakening",
      "confidence": "high",
      "source": "etf-history(window)",
      "href": "/research/etfs/xle/",
      "research_href": "/research/etfs/xle/",
      "evidence": [
        "intraseries window trend=weakening band=high from XLE OHLCV",
        "current rank state=weakening"
      ],
      "id": "084a21e1095c9c2f",
      "label_en": "weakening",
      "label_ar": "يضعف",
      "confidence_en": "high",
      "confidence_ar": "عالية"
    },
    {
      "entity": "XLF",
      "entity_type": "etf",
      "slug": "xlf",
      "timestamp": "2026-06-20T06:05:13.910Z",
      "from_state": null,
      "to_state": "improving",
      "change_type": "improving",
      "confidence": "high",
      "source": "etf-history(window)",
      "href": "/research/etfs/xlf/",
      "research_href": "/research/etfs/xlf/",
      "evidence": [
        "intraseries window trend=accelerating band=high from XLF OHLCV",
        "current rank state=improving"
      ],
      "id": "5ffec4f1933d4341",
      "label_en": "improving",
      "label_ar": "يتحسن",
      "confidence_en": "high",
      "confidence_ar": "عالية"
    },
    {
      "entity": "XLI",
      "entity_type": "etf",
      "slug": "xli",
      "timestamp": "2026-06-20T06:05:13.910Z",
      "from_state": null,
      "to_state": "improving",
      "change_type": "improving",
      "confidence": "high",
      "source": "etf-history(window)",
      "href": "/research/etfs/xli/",
      "research_href": "/research/etfs/xli/",
      "evidence": [
        "intraseries window trend=accelerating band=high from XLI OHLCV",
        "current rank state=improving"
      ],
      "id": "9f6efa5c2c0b9f4c",
      "label_en": "improving",
      "label_ar": "يتحسن",
      "confidence_en": "high",
      "confidence_ar": "عالية"
    },
    {
      "entity": "XLK",
      "entity_type": "etf",
      "slug": "xlk",
      "timestamp": "2026-06-20T06:05:13.910Z",
      "from_state": null,
      "to_state": "improving",
      "change_type": "stable",
      "confidence": "high",
      "source": "etf-history(window)",
      "href": "/research/etfs/xlk/",
      "research_href": "/research/etfs/xlk/",
      "evidence": [
        "intraseries window trend=stable band=high from XLK OHLCV",
        "current rank state=improving"
      ],
      "id": "3ffd61052da0c64e",
      "label_en": "stable",
      "label_ar": "مستقر",
      "confidence_en": "high",
      "confidence_ar": "عالية"
    },
    {
      "entity": "XLP",
      "entity_type": "etf",
      "slug": "xlp",
      "timestamp": "2026-06-20T06:05:13.910Z",
      "from_state": null,
      "to_state": "improving",
      "change_type": "deteriorating",
      "confidence": "high",
      "source": "etf-history(window)",
      "href": "/research/etfs/xlp/",
      "research_href": "/research/etfs/xlp/",
      "evidence": [
        "intraseries window trend=deteriorating band=high from XLP OHLCV",
        "current rank state=improving"
      ],
      "id": "971b861a33e436fc",
      "label_en": "deteriorating",
      "label_ar": "يتدهور",
      "confidence_en": "high",
      "confidence_ar": "عالية"
    },
    {
      "entity": "XLRE",
      "entity_type": "etf",
      "slug": "xlre",
      "timestamp": "2026-06-20T06:05:13.910Z",
      "from_state": null,
      "to_state": "improving",
      "change_type": "improving",
      "confidence": "high",
      "source": "etf-history(window)",
      "href": "/research/etfs/xlre/",
      "research_href": "/research/etfs/xlre/",
      "evidence": [
        "intraseries window trend=improving band=high from XLRE OHLCV",
        "current rank state=improving"
      ],
      "id": "284a8ab96cf99148",
      "label_en": "improving",
      "label_ar": "يتحسن",
      "confidence_en": "high",
      "confidence_ar": "عالية"
    },
    {
      "entity": "XLU",
      "entity_type": "etf",
      "slug": "xlu",
      "timestamp": "2026-06-20T06:05:13.910Z",
      "from_state": null,
      "to_state": "improving",
      "change_type": "improving",
      "confidence": "high",
      "source": "etf-history(window)",
      "href": "/research/etfs/xlu/",
      "research_href": "/research/etfs/xlu/",
      "evidence": [
        "intraseries window trend=accelerating band=high from XLU OHLCV",
        "current rank state=improving"
      ],
      "id": "14cfabcbfc0fd828",
      "label_en": "improving",
      "label_ar": "يتحسن",
      "confidence_en": "high",
      "confidence_ar": "عالية"
    },
    {
      "entity": "XLV",
      "entity_type": "etf",
      "slug": "xlv",
      "timestamp": "2026-06-20T06:05:13.910Z",
      "from_state": null,
      "to_state": "improving",
      "change_type": "deteriorating",
      "confidence": "high",
      "source": "etf-history(window)",
      "href": "/research/etfs/xlv/",
      "research_href": "/research/etfs/xlv/",
      "evidence": [
        "intraseries window trend=deteriorating band=high from XLV OHLCV",
        "current rank state=improving"
      ],
      "id": "2946439694830dba",
      "label_en": "deteriorating",
      "label_ar": "يتدهور",
      "confidence_en": "high",
      "confidence_ar": "عالية"
    },
    {
      "entity": "XLY",
      "entity_type": "etf",
      "slug": "xly",
      "timestamp": "2026-06-20T06:05:13.910Z",
      "from_state": null,
      "to_state": "improving",
      "change_type": "improving",
      "confidence": "high",
      "source": "etf-history(window)",
      "href": "/research/etfs/xly/",
      "research_href": "/research/etfs/xly/",
      "evidence": [
        "intraseries window trend=improving band=high from XLY OHLCV",
        "current rank state=improving"
      ],
      "id": "8a4c165e0489525f",
      "label_en": "improving",
      "label_ar": "يتحسن",
      "confidence_en": "high",
      "confidence_ar": "عالية"
    },
    {
      "entity": "IWM",
      "entity_type": "asset",
      "slug": "iwm",
      "timestamp": "2026-06-19T13:11:06.392Z",
      "from_state": null,
      "to_state": "strongest",
      "change_type": "leadership_gain",
      "confidence": "high",
      "source": "leadership-dashboard(window)",
      "href": "/markets/iwm/",
      "research_href": "/research/assets/iwm/",
      "evidence": [
        "leadership.strongest rank=strongest confirmation=confirmed",
        "historical direction=improving"
      ],
      "id": "869aeecfb1a1bbec",
      "label_en": "leadership gain",
      "label_ar": "اكتساب قيادة",
      "confidence_en": "high",
      "confidence_ar": "عالية"
    },
    {
      "entity": "XLF",
      "entity_type": "sector",
      "slug": "financials",
      "timestamp": "2026-06-19T13:11:06.392Z",
      "from_state": null,
      "to_state": "strongest",
      "change_type": "leadership_gain",
      "confidence": "moderate",
      "source": "leadership-dashboard(window)",
      "href": "/sectors/financials/",
      "research_href": "/research/sectors/financials/",
      "evidence": [
        "leadership.strongest rank=strongest confirmation=divergent",
        "historical direction=improving"
      ],
      "id": "482f01845de7d385",
      "label_en": "leadership gain",
      "label_ar": "اكتساب قيادة",
      "confidence_en": "moderate",
      "confidence_ar": "متوسطة"
    },
    {
      "entity": "XLI",
      "entity_type": "sector",
      "slug": "industrials",
      "timestamp": "2026-06-19T13:11:06.392Z",
      "from_state": null,
      "to_state": "strongest",
      "change_type": "leadership_gain",
      "confidence": "moderate",
      "source": "leadership-dashboard(window)",
      "href": "/sectors/industrials/",
      "research_href": "/research/sectors/industrials/",
      "evidence": [
        "leadership.strongest rank=strongest confirmation=divergent",
        "historical direction=improving"
      ],
      "id": "efbcafbfbe4647db",
      "label_en": "leadership gain",
      "label_ar": "اكتساب قيادة",
      "confidence_en": "moderate",
      "confidence_ar": "متوسطة"
    },
    {
      "entity": "XLRE",
      "entity_type": "sector",
      "slug": "real-estate",
      "timestamp": "2026-06-19T13:11:06.392Z",
      "from_state": null,
      "to_state": "strongest",
      "change_type": "leadership_gain",
      "confidence": "high",
      "source": "leadership-dashboard(window)",
      "href": "/sectors/real-estate/",
      "research_href": "/research/sectors/real-estate/",
      "evidence": [
        "leadership.strongest rank=strongest confirmation=confirmed",
        "historical direction=improving"
      ],
      "id": "06d38a593dd6a9cb",
      "label_en": "leadership gain",
      "label_ar": "اكتساب قيادة",
      "confidence_en": "high",
      "confidence_ar": "عالية"
    },
    {
      "entity": "XLV",
      "entity_type": "sector",
      "slug": "healthcare",
      "timestamp": "2026-06-19T13:11:06.392Z",
      "from_state": null,
      "to_state": "strongest",
      "change_type": "leadership_gain",
      "confidence": "moderate",
      "source": "leadership-dashboard(window)",
      "href": "/sectors/healthcare/",
      "research_href": "/research/sectors/healthcare/",
      "evidence": [
        "leadership.strongest rank=strongest confirmation=divergent",
        "historical direction=improving"
      ],
      "id": "853b3f33427fba25",
      "label_en": "leadership gain",
      "label_ar": "اكتساب قيادة",
      "confidence_en": "moderate",
      "confidence_ar": "متوسطة"
    },
    {
      "entity": "growth_momentum",
      "entity_type": "regime",
      "slug": null,
      "timestamp": "2026-06-18",
      "from_state": "risk-off",
      "to_state": "growth_momentum",
      "change_type": "regime_shift",
      "confidence": "high",
      "source": "regime-history",
      "href": null,
      "research_href": "/research/regime/",
      "evidence": [
        "regime transitioned risk-off → growth_momentum on 2026-06-18",
        "market_regime=growth_momentum",
        "defensive_rotation=absent"
      ],
      "id": "a1602e3198a62b25",
      "label_en": "regime shift",
      "label_ar": "تحول النظام",
      "confidence_en": "high",
      "confidence_ar": "عالية"
    },
    {
      "entity": "AAPL",
      "entity_type": "equity",
      "slug": "aapl",
      "timestamp": "2026-06-17T12:51:01.519Z",
      "from_state": null,
      "to_state": "deteriorating",
      "change_type": "deteriorating",
      "confidence": "high",
      "source": "equity-history",
      "href": "/equities/aapl/",
      "research_href": "/research/equities/aapl/",
      "evidence": [
        "equity-history overall=deteriorating band=high",
        "dimension trends: structure=deteriorating, tactical=deteriorating, liquidity=stable, participation=stable"
      ],
      "id": "c7fce2cd4e84ec06",
      "label_en": "deteriorating",
      "label_ar": "يتدهور",
      "confidence_en": "high",
      "confidence_ar": "عالية"
    },
    {
      "entity": "AMD",
      "entity_type": "equity",
      "slug": "amd",
      "timestamp": "2026-06-17T12:51:01.519Z",
      "from_state": null,
      "to_state": "deteriorating",
      "change_type": "deteriorating",
      "confidence": "high",
      "source": "equity-history",
      "href": "/equities/amd/",
      "research_href": "/research/equities/amd/",
      "evidence": [
        "equity-history overall=deteriorating band=high",
        "dimension trends: structure=stable, tactical=deteriorating, liquidity=stable, participation=stable"
      ],
      "id": "c98bdcbcc6a5ce3d",
      "label_en": "deteriorating",
      "label_ar": "يتدهور",
      "confidence_en": "high",
      "confidence_ar": "عالية"
    },
    {
      "entity": "AMZN",
      "entity_type": "equity",
      "slug": "amzn",
      "timestamp": "2026-06-17T12:51:01.519Z",
      "from_state": null,
      "to_state": "weakening",
      "change_type": "weakening",
      "confidence": "high",
      "source": "equity-history",
      "href": "/equities/amzn/",
      "research_href": "/research/equities/amzn/",
      "evidence": [
        "equity-history overall=weakening band=high",
        "dimension trends: structure=deteriorating, tactical=stable, liquidity=stable, participation=stable"
      ],
      "id": "31e40bd959a1f229",
      "label_en": "weakening",
      "label_ar": "يضعف",
      "confidence_en": "high",
      "confidence_ar": "عالية"
    },
    {
      "entity": "AVGO",
      "entity_type": "equity",
      "slug": "avgo",
      "timestamp": "2026-06-17T12:51:01.519Z",
      "from_state": null,
      "to_state": "weakening",
      "change_type": "weakening",
      "confidence": "high",
      "source": "equity-history",
      "href": "/equities/avgo/",
      "research_href": "/research/equities/avgo/",
      "evidence": [
        "equity-history overall=weakening band=high",
        "dimension trends: structure=deteriorating, tactical=deteriorating, liquidity=stable, participation=improving"
      ],
      "id": "118f6b9ec960a62e",
      "label_en": "weakening",
      "label_ar": "يضعف",
      "confidence_en": "high",
      "confidence_ar": "عالية"
    },
    {
      "entity": "GOOGL",
      "entity_type": "equity",
      "slug": "googl",
      "timestamp": "2026-06-17T12:51:01.519Z",
      "from_state": null,
      "to_state": "deteriorating",
      "change_type": "deteriorating",
      "confidence": "high",
      "source": "equity-history",
      "href": "/equities/googl/",
      "research_href": "/research/equities/googl/",
      "evidence": [
        "equity-history overall=deteriorating band=high",
        "dimension trends: structure=deteriorating, tactical=deteriorating, liquidity=stable, participation=stable"
      ],
      "id": "656b5855debff119",
      "label_en": "deteriorating",
      "label_ar": "يتدهور",
      "confidence_en": "high",
      "confidence_ar": "عالية"
    },
    {
      "entity": "META",
      "entity_type": "equity",
      "slug": "meta",
      "timestamp": "2026-06-17T12:51:01.519Z",
      "from_state": null,
      "to_state": "deteriorating",
      "change_type": "deteriorating",
      "confidence": "high",
      "source": "equity-history",
      "href": "/equities/meta/",
      "research_href": "/research/equities/meta/",
      "evidence": [
        "equity-history overall=deteriorating band=high",
        "dimension trends: structure=stable, tactical=deteriorating, liquidity=stable, participation=stable"
      ],
      "id": "f5f03a3aa0fc581f",
      "label_en": "deteriorating",
      "label_ar": "يتدهور",
      "confidence_en": "high",
      "confidence_ar": "عالية"
    },
    {
      "entity": "MSFT",
      "entity_type": "equity",
      "slug": "msft",
      "timestamp": "2026-06-17T12:51:01.519Z",
      "from_state": null,
      "to_state": "deteriorating",
      "change_type": "deteriorating",
      "confidence": "high",
      "source": "equity-history",
      "href": "/equities/msft/",
      "research_href": "/research/equities/msft/",
      "evidence": [
        "equity-history overall=deteriorating band=high",
        "dimension trends: structure=deteriorating, tactical=stable, liquidity=stable, participation=stable"
      ],
      "id": "f70e9ea5d17f6e1a",
      "label_en": "deteriorating",
      "label_ar": "يتدهور",
      "confidence_en": "high",
      "confidence_ar": "عالية"
    },
    {
      "entity": "NVDA",
      "entity_type": "equity",
      "slug": "nvda",
      "timestamp": "2026-06-17T12:51:01.519Z",
      "from_state": null,
      "to_state": "deteriorating",
      "change_type": "deteriorating",
      "confidence": "high",
      "source": "equity-history",
      "href": "/equities/nvda/",
      "research_href": "/research/equities/nvda/",
      "evidence": [
        "equity-history overall=deteriorating band=high",
        "dimension trends: structure=deteriorating, tactical=deteriorating, liquidity=stable, participation=stable"
      ],
      "id": "30bbda9f13bbc870",
      "label_en": "deteriorating",
      "label_ar": "يتدهور",
      "confidence_en": "high",
      "confidence_ar": "عالية"
    },
    {
      "entity": "PLTR",
      "entity_type": "equity",
      "slug": "pltr",
      "timestamp": "2026-06-17T12:51:01.519Z",
      "from_state": null,
      "to_state": "stable",
      "change_type": "stable",
      "confidence": "high",
      "source": "equity-history",
      "href": "/equities/pltr/",
      "research_href": "/research/equities/pltr/",
      "evidence": [
        "equity-history overall=stable band=high",
        "dimension trends: structure=stable, tactical=stable, liquidity=stable, participation=stable"
      ],
      "id": "7d73865c70e2874d",
      "label_en": "stable",
      "label_ar": "مستقر",
      "confidence_en": "high",
      "confidence_ar": "عالية"
    },
    {
      "entity": "SMCI",
      "entity_type": "equity",
      "slug": "smci",
      "timestamp": "2026-06-17T12:51:01.519Z",
      "from_state": null,
      "to_state": "weakening",
      "change_type": "weakening",
      "confidence": "high",
      "source": "equity-history",
      "href": "/equities/smci/",
      "research_href": "/research/equities/smci/",
      "evidence": [
        "equity-history overall=weakening band=high",
        "dimension trends: structure=deteriorating, tactical=deteriorating, liquidity=stable, participation=improving"
      ],
      "id": "de68cb7a04fab58e",
      "label_en": "weakening",
      "label_ar": "يضعف",
      "confidence_en": "high",
      "confidence_ar": "عالية"
    },
    {
      "entity": "TSLA",
      "entity_type": "equity",
      "slug": "tsla",
      "timestamp": "2026-06-17T12:51:01.519Z",
      "from_state": null,
      "to_state": "deteriorating",
      "change_type": "deteriorating",
      "confidence": "high",
      "source": "equity-history",
      "href": "/equities/tsla/",
      "research_href": "/research/equities/tsla/",
      "evidence": [
        "equity-history overall=deteriorating band=high",
        "dimension trends: structure=deteriorating, tactical=deteriorating, liquidity=stable, participation=stable"
      ],
      "id": "3a68ddc5e269b315",
      "label_en": "deteriorating",
      "label_ar": "يتدهور",
      "confidence_en": "high",
      "confidence_ar": "عالية"
    },
    {
      "entity": "XLB",
      "entity_type": "sector",
      "slug": "materials",
      "timestamp": "2026-06-17T12:51:01.515Z",
      "from_state": null,
      "to_state": "improving",
      "change_type": "improving",
      "confidence": "high",
      "source": "sector-history",
      "href": "/sectors/materials/",
      "research_href": "/research/sectors/materials/",
      "evidence": [
        "sector-history overall=improving band=high",
        "dimension trends: structure=stable, tactical=improving, liquidity=stable, participation=stable"
      ],
      "id": "0c2e357cf94cd658",
      "label_en": "improving",
      "label_ar": "يتحسن",
      "confidence_en": "high",
      "confidence_ar": "عالية"
    },
    {
      "entity": "XLE",
      "entity_type": "sector",
      "slug": "energy",
      "timestamp": "2026-06-17T12:51:01.515Z",
      "from_state": null,
      "to_state": "deteriorating",
      "change_type": "deteriorating",
      "confidence": "high",
      "source": "sector-history",
      "href": "/sectors/energy/",
      "research_href": "/research/sectors/energy/",
      "evidence": [
        "sector-history overall=deteriorating band=high",
        "dimension trends: structure=stable, tactical=deteriorating, liquidity=improving, participation=stable"
      ],
      "id": "14c0b5a1e764430c",
      "label_en": "deteriorating",
      "label_ar": "يتدهور",
      "confidence_en": "high",
      "confidence_ar": "عالية"
    },
    {
      "entity": "XLF",
      "entity_type": "sector",
      "slug": "financials",
      "timestamp": "2026-06-17T12:51:01.515Z",
      "from_state": null,
      "to_state": "accelerating",
      "change_type": "improving",
      "confidence": "high",
      "source": "sector-history",
      "href": "/sectors/financials/",
      "research_href": "/research/sectors/financials/",
      "evidence": [
        "sector-history overall=accelerating band=high",
        "dimension trends: structure=improving, tactical=improving, liquidity=stable, participation=stable"
      ],
      "id": "4fef2231233648da",
      "label_en": "improving",
      "label_ar": "يتحسن",
      "confidence_en": "high",
      "confidence_ar": "عالية"
    },
    {
      "entity": "XLI",
      "entity_type": "sector",
      "slug": "industrials",
      "timestamp": "2026-06-17T12:51:01.515Z",
      "from_state": null,
      "to_state": "accelerating",
      "change_type": "improving",
      "confidence": "high",
      "source": "sector-history",
      "href": "/sectors/industrials/",
      "research_href": "/research/sectors/industrials/",
      "evidence": [
        "sector-history overall=accelerating band=high",
        "dimension trends: structure=improving, tactical=improving, liquidity=improving, participation=stable"
      ],
      "id": "923723681c1b28bd",
      "label_en": "improving",
      "label_ar": "يتحسن",
      "confidence_en": "high",
      "confidence_ar": "عالية"
    },
    {
      "entity": "XLK",
      "entity_type": "sector",
      "slug": "technology",
      "timestamp": "2026-06-17T12:51:01.515Z",
      "from_state": null,
      "to_state": "deteriorating",
      "change_type": "deteriorating",
      "confidence": "high",
      "source": "sector-history",
      "href": "/sectors/technology/",
      "research_href": "/research/sectors/technology/",
      "evidence": [
        "sector-history overall=deteriorating band=high",
        "dimension trends: structure=stable, tactical=deteriorating, liquidity=stable, participation=stable"
      ],
      "id": "b31f9c42934977f4",
      "label_en": "deteriorating",
      "label_ar": "يتدهور",
      "confidence_en": "high",
      "confidence_ar": "عالية"
    },
    {
      "entity": "XLP",
      "entity_type": "sector",
      "slug": "consumer-staples",
      "timestamp": "2026-06-17T12:51:01.515Z",
      "from_state": null,
      "to_state": "deteriorating",
      "change_type": "deteriorating",
      "confidence": "high",
      "source": "sector-history",
      "href": "/sectors/consumer-staples/",
      "research_href": "/research/sectors/consumer-staples/",
      "evidence": [
        "sector-history overall=deteriorating band=high",
        "dimension trends: structure=deteriorating, tactical=stable, liquidity=stable, participation=stable"
      ],
      "id": "5af69e1e2760efba",
      "label_en": "deteriorating",
      "label_ar": "يتدهور",
      "confidence_en": "high",
      "confidence_ar": "عالية"
    },
    {
      "entity": "XLRE",
      "entity_type": "sector",
      "slug": "real-estate",
      "timestamp": "2026-06-17T12:51:01.515Z",
      "from_state": null,
      "to_state": "improving",
      "change_type": "improving",
      "confidence": "high",
      "source": "sector-history",
      "href": "/sectors/real-estate/",
      "research_href": "/research/sectors/real-estate/",
      "evidence": [
        "sector-history overall=improving band=high",
        "dimension trends: structure=improving, tactical=improving, liquidity=improving, participation=stable"
      ],
      "id": "ac04989c4cb12a47",
      "label_en": "improving",
      "label_ar": "يتحسن",
      "confidence_en": "high",
      "confidence_ar": "عالية"
    },
    {
      "entity": "XLU",
      "entity_type": "sector",
      "slug": "utilities",
      "timestamp": "2026-06-17T12:51:01.515Z",
      "from_state": null,
      "to_state": "improving",
      "change_type": "improving",
      "confidence": "high",
      "source": "sector-history",
      "href": "/sectors/utilities/",
      "research_href": "/research/sectors/utilities/",
      "evidence": [
        "sector-history overall=improving band=high",
        "dimension trends: structure=improving, tactical=improving, liquidity=stable, participation=stable"
      ],
      "id": "b6cea62106166213",
      "label_en": "improving",
      "label_ar": "يتحسن",
      "confidence_en": "high",
      "confidence_ar": "عالية"
    },
    {
      "entity": "XLV",
      "entity_type": "sector",
      "slug": "healthcare",
      "timestamp": "2026-06-17T12:51:01.515Z",
      "from_state": null,
      "to_state": "improving",
      "change_type": "improving",
      "confidence": "high",
      "source": "sector-history",
      "href": "/sectors/healthcare/",
      "research_href": "/research/sectors/healthcare/",
      "evidence": [
        "sector-history overall=improving band=high",
        "dimension trends: structure=improving, tactical=stable, liquidity=stable, participation=stable"
      ],
      "id": "7ec2d81efa3287be",
      "label_en": "improving",
      "label_ar": "يتحسن",
      "confidence_en": "high",
      "confidence_ar": "عالية"
    },
    {
      "entity": "XLY",
      "entity_type": "sector",
      "slug": "consumer-discretionary",
      "timestamp": "2026-06-17T12:51:01.515Z",
      "from_state": null,
      "to_state": "improving",
      "change_type": "improving",
      "confidence": "high",
      "source": "sector-history",
      "href": "/sectors/consumer-discretionary/",
      "research_href": "/research/sectors/consumer-discretionary/",
      "evidence": [
        "sector-history overall=improving band=high",
        "dimension trends: structure=stable, tactical=improving, liquidity=stable, participation=stable"
      ],
      "id": "b316e36dbaab4f6f",
      "label_en": "improving",
      "label_ar": "يتحسن",
      "confidence_en": "high",
      "confidence_ar": "عالية"
    },
    {
      "entity": "GLD",
      "entity_type": "asset",
      "slug": "gld",
      "timestamp": "2026-06-17T12:51:01.511Z",
      "from_state": null,
      "to_state": "deteriorating",
      "change_type": "deteriorating",
      "confidence": "high",
      "source": "asset-history",
      "href": "/markets/gld/",
      "research_href": "/research/assets/gld/",
      "evidence": [
        "asset-history overall=deteriorating band=high",
        "dimension trends: structure=deteriorating, tactical=deteriorating, liquidity=improving, participation=improving"
      ],
      "id": "f1842fda4bac5628",
      "label_en": "deteriorating",
      "label_ar": "يتدهور",
      "confidence_en": "high",
      "confidence_ar": "عالية"
    },
    {
      "entity": "IWM",
      "entity_type": "asset",
      "slug": "iwm",
      "timestamp": "2026-06-17T12:51:01.511Z",
      "from_state": null,
      "to_state": "improving",
      "change_type": "improving",
      "confidence": "high",
      "source": "asset-history",
      "href": "/markets/iwm/",
      "research_href": "/research/assets/iwm/",
      "evidence": [
        "asset-history overall=improving band=high",
        "dimension trends: structure=improving, tactical=improving, liquidity=improving, participation=stable"
      ],
      "id": "72311e2646e65a02",
      "label_en": "improving",
      "label_ar": "يتحسن",
      "confidence_en": "high",
      "confidence_ar": "عالية"
    },
    {
      "entity": "QQQ",
      "entity_type": "asset",
      "slug": "qqq",
      "timestamp": "2026-06-17T12:51:01.511Z",
      "from_state": null,
      "to_state": "deteriorating",
      "change_type": "deteriorating",
      "confidence": "high",
      "source": "asset-history",
      "href": "/markets/qqq/",
      "research_href": "/research/assets/qqq/",
      "evidence": [
        "asset-history overall=deteriorating band=high",
        "dimension trends: structure=stable, tactical=deteriorating, liquidity=stable, participation=improving"
      ],
      "id": "1560005e9c571515",
      "label_en": "deteriorating",
      "label_ar": "يتدهور",
      "confidence_en": "high",
      "confidence_ar": "عالية"
    },
    {
      "entity": "SPY",
      "entity_type": "asset",
      "slug": "spy",
      "timestamp": "2026-06-17T12:51:01.511Z",
      "from_state": null,
      "to_state": "stable",
      "change_type": "stable",
      "confidence": "high",
      "source": "asset-history",
      "href": "/markets/spy/",
      "research_href": "/research/assets/spy/",
      "evidence": [
        "asset-history overall=stable band=high",
        "dimension trends: structure=stable, tactical=deteriorating, liquidity=improving, participation=stable"
      ],
      "id": "e2e26a55751623e1",
      "label_en": "stable",
      "label_ar": "مستقر",
      "confidence_en": "high",
      "confidence_ar": "عالية"
    },
    {
      "entity": "TLT",
      "entity_type": "asset",
      "slug": "tlt",
      "timestamp": "2026-06-17T12:51:01.511Z",
      "from_state": null,
      "to_state": "accelerating",
      "change_type": "improving",
      "confidence": "high",
      "source": "asset-history",
      "href": "/markets/tlt/",
      "research_href": "/research/assets/tlt/",
      "evidence": [
        "asset-history overall=accelerating band=high",
        "dimension trends: structure=improving, tactical=improving, liquidity=stable, participation=stable"
      ],
      "id": "376f88566303c269",
      "label_en": "improving",
      "label_ar": "يتحسن",
      "confidence_en": "high",
      "confidence_ar": "عالية"
    },
    {
      "entity": "UUP",
      "entity_type": "asset",
      "slug": "uup",
      "timestamp": "2026-06-17T12:51:01.511Z",
      "from_state": null,
      "to_state": "improving",
      "change_type": "improving",
      "confidence": "high",
      "source": "asset-history",
      "href": "/markets/uup/",
      "research_href": "/research/assets/uup/",
      "evidence": [
        "asset-history overall=improving band=high",
        "dimension trends: structure=improving, tactical=deteriorating, liquidity=improving, participation=stable"
      ],
      "id": "e73c70008ea2f2a9",
      "label_en": "improving",
      "label_ar": "يتحسن",
      "confidence_en": "high",
      "confidence_ar": "عالية"
    },
    {
      "entity": "VIXY",
      "entity_type": "asset",
      "slug": "vixy",
      "timestamp": "2026-06-17T12:51:01.511Z",
      "from_state": null,
      "to_state": "stable",
      "change_type": "stable",
      "confidence": "high",
      "source": "asset-history",
      "href": "/markets/vixy/",
      "research_href": "/research/assets/vixy/",
      "evidence": [
        "asset-history overall=stable band=high",
        "dimension trends: structure=stable, tactical=stable, liquidity=stable, participation=stable"
      ],
      "id": "a42ede9edaa9f336",
      "label_en": "stable",
      "label_ar": "مستقر",
      "confidence_en": "high",
      "confidence_ar": "عالية"
    },
    {
      "entity": "risk-off",
      "entity_type": "regime",
      "slug": null,
      "timestamp": "2026-06-17",
      "from_state": "mixed",
      "to_state": "risk-off",
      "change_type": "regime_shift",
      "confidence": "high",
      "source": "regime-history",
      "href": null,
      "research_href": "/research/regime/",
      "evidence": [
        "regime transitioned mixed → risk-off on 2026-06-17",
        "market_regime=risk-off",
        "defensive_rotation=mixed"
      ],
      "id": "53bb1c7e328ee58d",
      "label_en": "regime shift",
      "label_ar": "تحول النظام",
      "confidence_en": "high",
      "confidence_ar": "عالية"
    },
    {
      "entity": "mixed",
      "entity_type": "regime",
      "slug": null,
      "timestamp": "2026-06-16",
      "from_state": "growth_momentum",
      "to_state": "mixed",
      "change_type": "regime_shift",
      "confidence": "high",
      "source": "regime-history",
      "href": null,
      "research_href": "/research/regime/",
      "evidence": [
        "regime transitioned growth_momentum → mixed on 2026-06-16",
        "market_regime=mixed",
        "defensive_rotation=present"
      ],
      "id": "6111d88aebb071d3",
      "label_en": "regime shift",
      "label_ar": "تحول النظام",
      "confidence_en": "high",
      "confidence_ar": "عالية"
    },
    {
      "entity": "growth_momentum",
      "entity_type": "regime",
      "slug": null,
      "timestamp": "2026-06-15",
      "from_state": "risk-on",
      "to_state": "growth_momentum",
      "change_type": "regime_shift",
      "confidence": "high",
      "source": "regime-history",
      "href": null,
      "research_href": "/research/regime/",
      "evidence": [
        "regime transitioned risk-on → growth_momentum on 2026-06-15",
        "market_regime=growth_momentum",
        "defensive_rotation=absent"
      ],
      "id": "e5e2d302e15ef208",
      "label_en": "regime shift",
      "label_ar": "تحول النظام",
      "confidence_en": "high",
      "confidence_ar": "عالية"
    }
  ],
  "by_category": {
    "asset": 8,
    "sector": 14,
    "equity": 11,
    "etf": 20,
    "regime": 4,
    "narrative": 0
  },
  "source_hash": "6cb82931a59c03069c3ad798f7abd115c650fafcfbc64a111e1f4b0bdba8dc41",
  "attribution": {
    "sources": [
      "data/intelligence/asset-history.json",
      "data/intelligence/sector-history.json",
      "data/intelligence/equity-history.json",
      "data/intelligence/etf-history.json",
      "data/intelligence/leadership-dashboard.json",
      "data/intelligence/regime-history.json",
      "data/intelligence/regime-transitions.json",
      "data/intelligence/market-narrative.json"
    ],
    "note": "Change events are derived from existing intelligence artifacts only. Every event carries an allowed change_type, a confidence band and evidence. Events without a determinate state or supporting prior are skipped (no fabrication)."
  }
}
