{
  "version": "1.0",
  "updated_at": "2026-07-09T16:05:14.166Z",
  "verified": true,
  "urgency": "elevated",
  "pulse_shift": [
    {
      "kind": "pulse-shift",
      "dimension": "momentum_concentration",
      "from": "narrow-megacap",
      "to": "balanced",
      "en": "momentum concentration shifted from narrow-megacap to balanced.",
      "ar": "تحولت حالة momentum concentration من narrow-megacap إلى balanced."
    },
    {
      "kind": "pulse-shift",
      "dimension": "ai_concentration_risk",
      "from": "elevated",
      "to": "contained",
      "en": "ai concentration risk shifted from elevated to contained.",
      "ar": "تحولت حالة ai concentration risk من elevated إلى contained."
    },
    {
      "kind": "pulse-shift",
      "dimension": "breadth_state",
      "from": "mixed",
      "to": "confirming",
      "en": "breadth state shifted from mixed to confirming.",
      "ar": "تحولت حالة breadth state من mixed إلى confirming."
    },
    {
      "kind": "pulse-shift",
      "dimension": "market_fragility",
      "from": "building",
      "to": "contained",
      "en": "market fragility shifted from building to contained.",
      "ar": "تحولت حالة market fragility من building إلى contained."
    }
  ],
  "quote_driven_changes": [
    {
      "kind": "quote-driven-change",
      "asset": "gold",
      "from": -0.8053,
      "to": 1.1377,
      "delta": 1.943,
      "en": "gold move changed by +1.94 percentage points.",
      "ar": "تغير تحرك gold بمقدار +1.94 نقطة مئوية."
    },
    {
      "kind": "quote-driven-change",
      "asset": "sp500",
      "from": -0.3089,
      "to": 0.6654,
      "delta": 0.9742999999999999,
      "en": "sp500 move changed by +0.97 percentage points.",
      "ar": "تغير تحرك sp500 بمقدار +0.97 نقطة مئوية."
    },
    {
      "kind": "quote-driven-change",
      "asset": "nasdaq",
      "from": 0.2833,
      "to": 1.511,
      "delta": 1.2277,
      "en": "nasdaq move changed by +1.23 percentage points.",
      "ar": "تغير تحرك nasdaq بمقدار +1.23 نقطة مئوية."
    },
    {
      "kind": "quote-driven-change",
      "asset": "bitcoin",
      "from": -2.0602,
      "to": 2.0444,
      "delta": 4.1046,
      "en": "bitcoin move changed by +4.10 percentage points.",
      "ar": "تغير تحرك bitcoin بمقدار +4.10 نقطة مئوية."
    },
    {
      "kind": "quote-driven-change",
      "asset": "vix",
      "from": 4.643962848297214,
      "to": 3.468208092485544,
      "delta": -1.17575475581167,
      "en": "vix move changed by -1.18 percentage points.",
      "ar": "تغير تحرك vix بمقدار -1.18 نقطة مئوية."
    },
    {
      "kind": "quote-driven-change",
      "asset": "us10y_yield",
      "from": 2.100558659217884,
      "to": 1.3823857302118034,
      "delta": -0.7181729290060808,
      "en": "us10y yield move changed by -0.72 percentage points.",
      "ar": "تغير تحرك us10y yield بمقدار -0.72 نقطة مئوية."
    }
  ],
  "new_contradictions": [],
  "pressure_buildup": [],
  "new_alerts": [],
  "catalyst_countdown": [
    {
      "name": "FOMC Press Release",
      "time": "2026-07-09T00:00:00Z",
      "minutes_until": 0
    },
    {
      "name": "Initial Jobless Claims",
      "time": "2026-07-09T12:30:00.000Z",
      "minutes_until": 0
    },
    {
      "name": "FOMC Press Release",
      "time": "2026-07-10T00:00:00Z",
      "minutes_until": 475
    }
  ],
  "wire_event": {
    "headline": "NVDA jumps +3.65% to 204.12",
    "timestamp": "2026-07-08T21:44:23.309Z",
    "urgency": 90
  },
  "changes": [
    {
      "kind": "pulse-shift",
      "dimension": "momentum_concentration",
      "from": "narrow-megacap",
      "to": "balanced",
      "en": "momentum concentration shifted from narrow-megacap to balanced.",
      "ar": "تحولت حالة momentum concentration من narrow-megacap إلى balanced."
    },
    {
      "kind": "pulse-shift",
      "dimension": "ai_concentration_risk",
      "from": "elevated",
      "to": "contained",
      "en": "ai concentration risk shifted from elevated to contained.",
      "ar": "تحولت حالة ai concentration risk من elevated إلى contained."
    },
    {
      "kind": "pulse-shift",
      "dimension": "breadth_state",
      "from": "mixed",
      "to": "confirming",
      "en": "breadth state shifted from mixed to confirming.",
      "ar": "تحولت حالة breadth state من mixed إلى confirming."
    },
    {
      "kind": "pulse-shift",
      "dimension": "market_fragility",
      "from": "building",
      "to": "contained",
      "en": "market fragility shifted from building to contained.",
      "ar": "تحولت حالة market fragility من building إلى contained."
    },
    {
      "kind": "quote-driven-change",
      "asset": "gold",
      "from": -0.8053,
      "to": 1.1377,
      "delta": 1.943,
      "en": "gold move changed by +1.94 percentage points.",
      "ar": "تغير تحرك gold بمقدار +1.94 نقطة مئوية."
    },
    {
      "kind": "quote-driven-change",
      "asset": "sp500",
      "from": -0.3089,
      "to": 0.6654,
      "delta": 0.9742999999999999,
      "en": "sp500 move changed by +0.97 percentage points.",
      "ar": "تغير تحرك sp500 بمقدار +0.97 نقطة مئوية."
    },
    {
      "kind": "quote-driven-change",
      "asset": "nasdaq",
      "from": 0.2833,
      "to": 1.511,
      "delta": 1.2277,
      "en": "nasdaq move changed by +1.23 percentage points.",
      "ar": "تغير تحرك nasdaq بمقدار +1.23 نقطة مئوية."
    },
    {
      "kind": "quote-driven-change",
      "asset": "bitcoin",
      "from": -2.0602,
      "to": 2.0444,
      "delta": 4.1046,
      "en": "bitcoin move changed by +4.10 percentage points.",
      "ar": "تغير تحرك bitcoin بمقدار +4.10 نقطة مئوية."
    },
    {
      "kind": "quote-driven-change",
      "asset": "vix",
      "from": 4.643962848297214,
      "to": 3.468208092485544,
      "delta": -1.17575475581167,
      "en": "vix move changed by -1.18 percentage points.",
      "ar": "تغير تحرك vix بمقدار -1.18 نقطة مئوية."
    },
    {
      "kind": "quote-driven-change",
      "asset": "us10y_yield",
      "from": 2.100558659217884,
      "to": 1.3823857302118034,
      "delta": -0.7181729290060808,
      "en": "us10y yield move changed by -0.72 percentage points.",
      "ar": "تغير تحرك us10y yield بمقدار -0.72 نقطة مئوية."
    }
  ],
  "note_en": null,
  "note_ar": null,
  "telegram": {
    "eligible": false,
    "sent": false,
    "suppression_reason": "urgency_below_high_threshold"
  },
  "snapshot": {
    "verified": true,
    "dimensions": {
      "risk_state": "risk-on",
      "volatility_regime": "normal",
      "dollar_pressure": "stable",
      "duration_pressure": "neutral",
      "momentum_concentration": "balanced",
      "ai_concentration_risk": "contained",
      "breadth_state": "confirming",
      "defensive_rotation": "unverified",
      "liquidity_stress": "mixed",
      "speculative_appetite": "unverified",
      "market_fragility": "contained"
    },
    "quote_changes": {
      "gold": 1.1377,
      "dxy": 0.016856717897878154,
      "sp500": 0.6654,
      "nasdaq": 1.511,
      "bitcoin": 2.0444,
      "vix": 3.468208092485544,
      "us10y_yield": 1.3823857302118034,
      "nvda": -0.9553,
      "oil": 5.22246535375638
    },
    "alert_ids": [],
    "alerts": [],
    "contradiction_ids": [],
    "pressure": {
      "volatility_pressure": 0,
      "liquidity_pressure": 3,
      "defensive_pressure": 0,
      "speculative_pressure": 3,
      "concentration_pressure": 5,
      "yield_pressure": 0
    },
    "catalysts": [
      {
        "name": "FOMC Press Release",
        "time": "2026-07-09T00:00:00Z"
      },
      {
        "name": "Initial Jobless Claims",
        "time": "2026-07-09T12:30:00.000Z"
      },
      {
        "name": "FOMC Press Release",
        "time": "2026-07-10T00:00:00Z"
      }
    ],
    "wire_event": {
      "headline": "NVDA jumps +3.65% to 204.12",
      "timestamp": "2026-07-08T21:44:23.309Z",
      "urgency": 90
    }
  },
  "disclaimer": {
    "en": "Educational monitoring context only. Not investment advice.",
    "ar": "سياق متابعة تعليمي فقط، وليس نصيحة استثمارية."
  }
}
