{
  "timestamp": "2026-07-13T12:36:27.695Z",
  "brain_mode": "full_pipeline",
  "selected_topic": "market-regime-2026-06-30",
  "selected_content_type": "market-outlook",
  "generation_result": "draft generated",
  "publish_result": "published after autonomous approval",
  "published": true,
  "site_update": false,
  "commit_allowed": true,
  "fallback_attempts": [
    {
      "content_type": "market-outlook",
      "topic": "market-regime-2026-06-30",
      "result": "published after autonomous approval"
    }
  ],
  "site_update_results": [],
  "publish_block_reason": "",
  "telegram_sent": true,
  "public_pages_created": [
    "market-outlook/market-regime-2026-06-30.html",
    "en/market-outlook/market-regime-2026-06-30.html",
    "ar/market-outlook/market-regime-2026-06-30.html"
  ],
  "drafts_created": [
    "drafts/market-outlook/market-regime-2026-06-30/en.html",
    "drafts/market-outlook/market-regime-2026-06-30/ar.html"
  ],
  "quality_score": 90,
  "approval_state": "published",
  "cooldown_blocked": false,
  "manual_review_required": false
}
