{
  "version": "1.0",
  "updated_at": "2026-06-15T15:32:36.262Z",
  "sessions": [
    {
      "date": "2026-06-12",
      "updated_at": "2026-06-12T18:25:22.295Z",
      "verified": true,
      "dims": {
        "risk_state": "unverified",
        "volatility_regime": "unverified",
        "dollar_pressure": "unverified",
        "duration_pressure": "unverified",
        "momentum_concentration": "balanced",
        "ai_concentration_risk": "contained",
        "breadth_state": "confirming",
        "defensive_rotation": "unverified",
        "liquidity_stress": "unverified",
        "speculative_appetite": "unverified",
        "market_fragility": "contained"
      },
      "sourced_moves": {
        "gold": 0.5203,
        "dxy": null,
        "spy": 0.3795,
        "qqq": 0.495,
        "iwm": 0.9779,
        "vix": null,
        "nvda": -0.2489,
        "btc": null,
        "us10y": null,
        "tlt": -0.2559
      },
      "divergences": [],
      "live_status": "live"
    },
    {
      "date": "2026-06-13",
      "updated_at": "2026-06-13T23:10:48.768Z",
      "verified": true,
      "dims": {
        "risk_state": "unverified",
        "volatility_regime": "unverified",
        "dollar_pressure": "unverified",
        "duration_pressure": "unverified",
        "momentum_concentration": "balanced",
        "ai_concentration_risk": "contained",
        "breadth_state": "confirming",
        "defensive_rotation": "unverified",
        "liquidity_stress": "unverified",
        "speculative_appetite": "unverified",
        "market_fragility": "contained"
      },
      "sourced_moves": {
        "gold": 0.0569,
        "dxy": null,
        "spy": 0.5408,
        "qqq": 0.5885,
        "iwm": 0.8746,
        "vix": null,
        "nvda": 0.1562,
        "btc": null,
        "us10y": null,
        "tlt": -0.2442
      },
      "divergences": [],
      "live_status": "live"
    },
    {
      "date": "2026-06-15",
      "updated_at": "2026-06-15T15:32:36.262Z",
      "verified": true,
      "dims": {
        "risk_state": "unverified",
        "volatility_regime": "unverified",
        "dollar_pressure": "unverified",
        "duration_pressure": "unverified",
        "momentum_concentration": "narrow-megacap",
        "ai_concentration_risk": "contained",
        "breadth_state": "confirming",
        "defensive_rotation": "unverified",
        "liquidity_stress": "unverified",
        "speculative_appetite": "expanding",
        "market_fragility": "building"
      },
      "sourced_moves": {
        "gold": 3.3787,
        "dxy": null,
        "spy": 1.82,
        "qqq": 3.036,
        "iwm": 0.9217,
        "vix": null,
        "nvda": 2.9046,
        "btc": null,
        "us10y": null,
        "tlt": 0.0933
      },
      "divergences": [],
      "live_status": "live"
    }
  ]
}
