{
  "version": "1.0",
  "updated_at": "2026-06-15T15:32:36.360Z",
  "run_date": "2026-06-15",
  "verified": false,
  "status": "holding_unverified",
  "regime_condition": "unverified",
  "tension_level": "unverified",
  "tension_score": null,
  "tracks": {},
  "active_strains": [],
  "internal_stability": null,
  "narrative_stability": "unverified",
  "catalyst_fragility": {
    "level": "unverified",
    "next": null
  },
  "strain_map": [],
  "pressure_memory": [
    {
      "date": "2026-06-12",
      "condition": "stable-regime",
      "score": 5,
      "change": "initialized"
    },
    {
      "date": "2026-06-13",
      "condition": "stable-regime",
      "score": 0,
      "change": "faded"
    }
  ],
  "summary_en": "Structural tension assessment is held until the intelligence stack is fully verified.",
  "summary_ar": "يظل تقييم التوتر الهيكلي معلقاً إلى حين اكتمال توثيق منظومة الاستخبارات."
}
