{
  "version": "2.0",
  "updated_at": "2026-07-16T11:46:00.978Z",
  "mode": "preview_only",
  "posting_enabled": false,
  "previews": [
    {
      "platform": "telegram",
      "language": "en",
      "source_artifact": "data/intelligence/daily-intelligence-brief.json",
      "source_story_id": "session-2026-07-16",
      "generated_at": "2026-07-16T11:46:00.978Z",
      "title": "Market structure brief",
      "hook": "Regime coherence 50/100 — the tape is internally tense; confirmations and divergences are competing.",
      "body": "Regime coherence 50/100 — the tape is internally tense; confirmations and divergences are competing. • Divergence in focus: Rising yields mark down long-duration bonds. • Next scheduled test: FOMC Press Release. In focus: QQQ · DXY · US10Y · SPY · BTC · TLT · NVDA · GOLD",
      "cta": "Read the full context: https://www.tradealphaai.com/",
      "evidence_references": [
        "data/intelligence/daily-intelligence-brief.json",
        "data/intelligence/narrative-convergence.json",
        "data/intelligence/chart-narratives.json"
      ],
      "related_symbols": [
        "QQQ",
        "DXY",
        "US10Y",
        "SPY",
        "BTC",
        "TLT",
        "NVDA",
        "GOLD"
      ],
      "hashtags": [
        "#Markets",
        "#Macro",
        "#MarketIntelligence"
      ],
      "no_advice": true,
      "dedupe_hash": "092a639b613475d9081f",
      "source_hash": "8215807eecc25b0f1e07",
      "content_hash": "8dfaef0c84a41840e19c",
      "visual_recommendation": {
        "type": "chart-card",
        "chart_id": "liquidity-beta",
        "visual_type": "liquidity-pressure",
        "symbols": [
          "CRYPTO:BTCUSD",
          "NASDAQ:QQQ"
        ],
        "title": "Liquidity beta",
        "attribution": "Chart: TradingView · Quotes: sourced market providers",
        "render": false
      },
      "urgency_level": "high",
      "distribution_relevance_score": 100,
      "distribution_status": "suppressed",
      "suppression_reasons": [
        "repeated_hook",
        "repeated_headline",
        "narrative_overlap"
      ],
      "approval_required": true,
      "auto_post_allowed": false,
      "cooldown_hours": 6,
      "disclaimer": "Educational market context only. Not investment advice."
    },
    {
      "platform": "telegram",
      "language": "ar",
      "source_artifact": "data/intelligence/daily-intelligence-brief.json",
      "source_story_id": "session-2026-07-16",
      "generated_at": "2026-07-16T11:46:00.978Z",
      "title": "موجز بنية السوق",
      "hook": "اتساق النظام 50/100 — السوق مشدود داخلياً؛ التأكيدات والانفصالات تتنافس.",
      "body": "اتساق النظام 50/100 — السوق مشدود داخلياً؛ التأكيدات والانفصالات تتنافس. • موضع التباعد الأبرز: ارتفاع العوائد يخفض السندات طويلة الأمد. • الاختبار المجدول التالي: FOMC Press Release. تحت المجهر: QQQ · DXY · US10Y · SPY · BTC · TLT · NVDA · GOLD",
      "cta": "اقرأ السياق الكامل: https://www.tradealphaai.com/ar/",
      "evidence_references": [
        "data/intelligence/daily-intelligence-brief.json",
        "data/intelligence/narrative-convergence.json",
        "data/intelligence/chart-narratives.json"
      ],
      "related_symbols": [
        "QQQ",
        "DXY",
        "US10Y",
        "SPY",
        "BTC",
        "TLT",
        "NVDA",
        "GOLD"
      ],
      "hashtags": [
        "#الأسواق",
        "#الاقتصاد_الكلي",
        "#استخبارات_السوق"
      ],
      "no_advice": true,
      "dedupe_hash": "ab3d2542fa3fcb5c07ee",
      "source_hash": "8215807eecc25b0f1e07",
      "content_hash": "2e7a35de85cc2834658c",
      "visual_recommendation": {
        "type": "chart-card",
        "chart_id": "liquidity-beta",
        "visual_type": "liquidity-pressure",
        "symbols": [
          "CRYPTO:BTCUSD",
          "NASDAQ:QQQ"
        ],
        "title": "بيتا السيولة",
        "attribution": "Chart: TradingView · Quotes: sourced market providers",
        "render": false
      },
      "urgency_level": "high",
      "distribution_relevance_score": 100,
      "distribution_status": "suppressed",
      "suppression_reasons": [
        "repeated_hook",
        "repeated_headline",
        "narrative_overlap"
      ],
      "approval_required": true,
      "auto_post_allowed": false,
      "cooldown_hours": 6,
      "disclaimer": "سياق تعليمي للأسواق فقط، وليس نصيحة استثمارية."
    }
  ]
}
