{
  "version": "2.0",
  "generated_at": "2026-07-21T21:20:39.510Z",
  "metadata": {
    "status": "live",
    "data_quality": "full",
    "fields_populated": 12,
    "source_policy": {
      "description": "Values fetched from FRED and Finnhub APIs with caching. No fabricated or AI-inferred values.",
      "update_tool": "tools/update-live-market-state.js --fetch --write",
      "staleness_threshold_hours": 26,
      "fallback_on_stale": true
    }
  },
  "sp500": {
    "value": 748.28,
    "change_pct": 0.8341,
    "source_url": "https://finnhub.io/",
    "source_name": "Finnhub",
    "fetched_at": "2026-07-21T21:20:37.897Z"
  },
  "nasdaq": {
    "value": 708.97,
    "change_pct": 1.8547,
    "source_url": "https://finnhub.io/",
    "source_name": "Finnhub",
    "fetched_at": "2026-07-21T21:20:37.897Z"
  },
  "dowjones": {
    "value": 52224.64,
    "change_pct": -0.5401625305880339,
    "source_url": "https://finance.yahoo.com/",
    "source_name": "Yahoo Finance",
    "fetched_at": "2026-07-21T21:20:40.812Z"
  },
  "russell2000": {
    "value": 296.54,
    "change_pct": 1.4471,
    "source_url": "https://finnhub.io/",
    "source_name": "Finnhub",
    "fetched_at": "2026-07-21T21:20:37.897Z"
  },
  "vix": {
    "value": 17.05,
    "change_pct": 8.80663688576899,
    "source_url": "https://finance.yahoo.com/",
    "source_name": "Yahoo Finance",
    "fetched_at": "2026-07-21T21:20:39.746Z"
  },
  "us10y_yield": {
    "value": 4.628,
    "change_pct": 1.8261826182618304,
    "source_url": "https://finance.yahoo.com/",
    "source_name": "Yahoo Finance",
    "fetched_at": "2026-07-21T21:20:40.488Z"
  },
  "us2y_yield": {
    "value": null,
    "change_pct": null,
    "source_url": null,
    "source_name": null,
    "fetched_at": null
  },
  "fed_funds_rate": {
    "value": null,
    "change_pct": null,
    "source_url": null,
    "source_name": null,
    "fetched_at": null
  },
  "dxy": {
    "value": 101.195,
    "change_pct": 0.46163010026803253,
    "source_url": "https://finance.yahoo.com/",
    "source_name": "Yahoo Finance",
    "fetched_at": "2026-07-21T21:20:40.105Z"
  },
  "gold": {
    "value": 374.81,
    "change_pct": 1.9614,
    "source_url": "https://finnhub.io/",
    "source_name": "Finnhub",
    "fetched_at": "2026-07-21T21:20:37.897Z"
  },
  "bitcoin": {
    "value": 66340.21,
    "change_pct": 1.5533,
    "source_url": "https://finnhub.io/",
    "source_name": "Finnhub",
    "fetched_at": "2026-07-21T21:20:37.897Z"
  },
  "nvda": {
    "value": 207.29,
    "change_pct": 1.9726,
    "source_url": "https://finnhub.io/",
    "source_name": "Finnhub",
    "fetched_at": "2026-07-21T21:20:37.897Z"
  },
  "tlt": {
    "value": 83.66,
    "change_pct": -0.2742,
    "source_url": "https://finnhub.io/",
    "source_name": "Finnhub",
    "fetched_at": "2026-07-21T21:20:37.897Z"
  },
  "oil": {
    "value": 84.54,
    "change_pct": 7.080430652311594,
    "source_url": "https://finance.yahoo.com/",
    "source_name": "Yahoo Finance",
    "fetched_at": "2026-07-21T21:20:41.194Z"
  },
  "yield_spread_2y10y": {
    "value": null,
    "spread_bps": null,
    "spread_regime": null,
    "computed_at": null
  },
  "sector_etfs": {
    "XLK": {
      "price": 180.78,
      "change_pct": 2.8854,
      "source": "Finnhub",
      "fetched_at": "2026-07-21T21:20:39.510Z"
    },
    "XLF": {
      "price": 56.11,
      "change_pct": 0.1249,
      "source": "Finnhub",
      "fetched_at": "2026-07-21T21:20:39.510Z"
    },
    "XLE": {
      "price": 58.5,
      "change_pct": 0.9665,
      "source": "Finnhub",
      "fetched_at": "2026-07-21T21:20:39.510Z"
    },
    "XLU": {
      "price": 44.92,
      "change_pct": -0.0445,
      "source": "Finnhub",
      "fetched_at": "2026-07-21T21:20:39.510Z"
    },
    "XLV": {
      "price": 160.25,
      "change_pct": 0.6279,
      "source": "Finnhub",
      "fetched_at": "2026-07-21T21:20:39.510Z"
    },
    "XLI": {
      "price": 178.66,
      "change_pct": 0.3032,
      "source": "Finnhub",
      "fetched_at": "2026-07-21T21:20:39.510Z"
    },
    "XLRE": {
      "price": 45.2,
      "change_pct": -0.0663,
      "source": "Finnhub",
      "fetched_at": "2026-07-21T21:20:39.510Z"
    },
    "XLP": {
      "price": 84.06,
      "change_pct": -0.9427,
      "source": "Finnhub",
      "fetched_at": "2026-07-21T21:20:39.510Z"
    }
  },
  "computed_regime": {
    "volatility_regime": "normal",
    "risk_regime": "risk-on",
    "market_regime": "growth_momentum",
    "ai_sector_momentum": "positive",
    "semiconductor_strength": "neutral",
    "rates_trend": "unverified",
    "defensive_rotation": "absent",
    "growth_value_bias": "growth",
    "sector_leadership": [
      "XLK",
      "XLE",
      "XLV"
    ],
    "sector_weakness": [
      "XLP"
    ],
    "yield_spread": null,
    "vix_level": 17.05,
    "computed_at": "2026-07-21T21:20:41.395Z"
  },
  "sector_leadership": [
    "XLK",
    "XLE",
    "XLV"
  ],
  "sector_weakness": [
    "XLP"
  ],
  "macro_summary": "VIX 17.1 (normal volatility). Equity moves: SPY +0.83% · QQQ +1.85% · IWM +1.45%. Yields: 10Y 4.63%. DXY 101.2. GLD $374.8 (+1.96%). Sector leaders: XLK +2.89% XLE +0.97% XLV +0.63%. Laggards: XLP -0.94%. Regime: growth_momentum",
  "fed_expectations": null
}
