{
  "version": "2.0",
  "generated_at": "2026-07-07T15:46:02.351Z",
  "metadata": {
    "status": "live",
    "data_quality": "full",
    "fields_populated": 12,
    "source_policy": {
      "description": "Values fetched from FRED and Finnhub APIs with caching. No fabricated or AI-inferred values.",
      "update_tool": "tools/update-live-market-state.js --fetch --write",
      "staleness_threshold_hours": 26,
      "fallback_on_stale": true
    }
  },
  "sp500": {
    "value": 746.53,
    "change_pct": -0.6323,
    "source_url": "https://finnhub.io/",
    "source_name": "Finnhub",
    "fetched_at": "2026-07-07T15:46:00.484Z"
  },
  "nasdaq": {
    "value": 707.8,
    "change_pct": -2.078,
    "source_url": "https://finnhub.io/",
    "source_name": "Finnhub",
    "fetched_at": "2026-07-07T15:46:00.484Z"
  },
  "dowjones": {
    "value": 52871.43,
    "change_pct": 1.31976588427515,
    "source_url": "https://finance.yahoo.com/",
    "source_name": "Yahoo Finance",
    "fetched_at": "2026-07-07T15:46:03.149Z"
  },
  "russell2000": {
    "value": 296.74,
    "change_pct": -0.7226,
    "source_url": "https://finnhub.io/",
    "source_name": "Finnhub",
    "fetched_at": "2026-07-07T15:46:00.484Z"
  },
  "vix": {
    "value": 16.39,
    "change_pct": -1.2055455093429734,
    "source_url": "https://finance.yahoo.com/",
    "source_name": "Yahoo Finance",
    "fetched_at": "2026-07-07T15:46:02.403Z"
  },
  "us10y_yield": {
    "value": 4.511,
    "change_pct": 2.105024898143956,
    "source_url": "https://finance.yahoo.com/",
    "source_name": "Yahoo Finance",
    "fetched_at": "2026-07-07T15:46:02.909Z"
  },
  "us2y_yield": {
    "value": null,
    "change_pct": null,
    "source_url": null,
    "source_name": null,
    "fetched_at": null
  },
  "fed_funds_rate": {
    "value": null,
    "change_pct": null,
    "source_url": null,
    "source_name": null,
    "fetched_at": null
  },
  "dxy": {
    "value": 100.952,
    "change_pct": -0.4319952658053086,
    "source_url": "https://finance.yahoo.com/",
    "source_name": "Yahoo Finance",
    "fetched_at": "2026-07-07T15:46:02.646Z"
  },
  "gold": {
    "value": 380.56,
    "change_pct": -0.4109,
    "source_url": "https://finnhub.io/",
    "source_name": "Finnhub",
    "fetched_at": "2026-07-07T15:46:00.484Z"
  },
  "bitcoin": {
    "value": 63994,
    "change_pct": 1.7587,
    "source_url": "https://finnhub.io/",
    "source_name": "Finnhub",
    "fetched_at": "2026-07-07T15:46:00.484Z"
  },
  "nvda": {
    "value": 193.45,
    "change_pct": -1.0739,
    "source_url": "https://finnhub.io/",
    "source_name": "Finnhub",
    "fetched_at": "2026-07-07T15:46:00.484Z"
  },
  "tlt": {
    "value": 84.85,
    "change_pct": -0.7022,
    "source_url": "https://finnhub.io/",
    "source_name": "Finnhub",
    "fetched_at": "2026-07-07T15:46:00.484Z"
  },
  "oil": {
    "value": 70.22,
    "change_pct": 2.3913677456984552,
    "source_url": "https://finance.yahoo.com/",
    "source_name": "Yahoo Finance",
    "fetched_at": "2026-07-07T15:46:03.390Z"
  },
  "yield_spread_2y10y": {
    "value": null,
    "spread_bps": null,
    "spread_regime": null,
    "computed_at": null
  },
  "sector_etfs": {
    "XLK": {
      "price": 178.44,
      "change_pct": -2.7946,
      "source": "Finnhub",
      "fetched_at": "2026-07-07T15:46:02.351Z"
    },
    "XLF": {
      "price": 56.29,
      "change_pct": 0.2672,
      "source": "Finnhub",
      "fetched_at": "2026-07-07T15:46:02.351Z"
    },
    "XLE": {
      "price": 54.04,
      "change_pct": 1.7128,
      "source": "Finnhub",
      "fetched_at": "2026-07-07T15:46:02.351Z"
    },
    "XLU": {
      "price": 45.96,
      "change_pct": 1.457,
      "source": "Finnhub",
      "fetched_at": "2026-07-07T15:46:02.351Z"
    },
    "XLV": {
      "price": 164.85,
      "change_pct": 1.7844,
      "source": "Finnhub",
      "fetched_at": "2026-07-07T15:46:02.351Z"
    },
    "XLI": {
      "price": 180.9,
      "change_pct": -2.5113,
      "source": "Finnhub",
      "fetched_at": "2026-07-07T15:46:02.351Z"
    },
    "XLRE": {
      "price": 45.08,
      "change_pct": 1.7837,
      "source": "Finnhub",
      "fetched_at": "2026-07-07T15:46:02.351Z"
    },
    "XLP": {
      "price": 85.22,
      "change_pct": 1.3317,
      "source": "Finnhub",
      "fetched_at": "2026-07-07T15:46:02.351Z"
    }
  },
  "computed_regime": {
    "volatility_regime": "normal",
    "risk_regime": "neutral",
    "market_regime": "mixed",
    "ai_sector_momentum": "negative",
    "semiconductor_strength": "neutral",
    "rates_trend": "unverified",
    "defensive_rotation": "present",
    "growth_value_bias": "value",
    "sector_leadership": [
      "XLV",
      "XLRE",
      "XLE"
    ],
    "sector_weakness": [
      "XLK",
      "XLI"
    ],
    "yield_spread": null,
    "vix_level": 16.39,
    "computed_at": "2026-07-07T15:46:03.591Z"
  },
  "sector_leadership": [
    "XLV",
    "XLRE",
    "XLE"
  ],
  "sector_weakness": [
    "XLK",
    "XLI"
  ],
  "macro_summary": "VIX 16.4 (normal volatility). Equity moves: SPY -0.63% · QQQ -2.08% · IWM -0.72%. Yields: 10Y 4.51%. DXY 101.0. GLD $380.6 (-0.41%). Sector leaders: XLV +1.78% XLRE +1.78% XLE +1.71%. Laggards: XLK -2.79% XLI -2.51%. Regime: mixed",
  "fed_expectations": null
}
