{
  "version": "1.0",
  "updated": "2026-06-03",
  "policy": {
    "content_type": "market_outlook",
    "auto_publish": false,
    "requires_editorial_review": true,
    "publish_cadence": "4 per week",
    "allowed_statuses": [
      "planned",
      "draft",
      "in_review",
      "reviewed",
      "published"
    ],
    "forbidden": [
      "buy/sell recommendations",
      "fabricated predictions",
      "fake catalysts",
      "guaranteed returns",
      "certain price targets"
    ],
    "disclaimer_en": "This content is educational market commentary only and does not constitute financial advice or investment recommendations.",
    "disclaimer_ar": "هذا المحتوى عبارة عن تحليل وتعليق تعليمي للأسواق فقط ولا يُعتبر نصيحة مالية أو توصية شراء أو بيع."
  },
  "topics": []
}
