{
  "slug": "healthcare-etf-research-guide",
  "title": "دليل بحث صناديق الرعاية الصحية: السمات الدفاعية ومخاطر القطاع",
  "category": "أبحاث القطاعات",
  "readingTime": "7 دقائق قراءة",
  "lead": "دليل بحث صناديق الرعاية الصحية: السمات الدفاعية ومخاطر القطاع ضمن بحث تعليمي دائم حول الأسواق، مع التركيز على المخاطر والتنويع والروابط البحثية ذات الصلة دون تقديم نصيحة مالية.",
  "summary": "",
  "sections": [],
  "faq": [
    {
      "q": "هل هذا المحتوى نصيحة مالية؟",
      "a": "لا. هذا المحتوى تعليمي فقط ولا يقدم توصية بشراء أو بيع أي ورقة مالية."
    },
    {
      "q": "ما الذي يجب مراجعته قبل النشر؟",
      "a": "يجب مراجعة الدقة اللغوية، الروابط، المخطط المنظم، التكافؤ بين الإنجليزية والعربية، وأي عبارة قد تبدو زمنية أو توصية مباشرة."
    },
    {
      "q": "كيف يستخدم القارئ هذا البحث؟",
      "a": "يمكن استخدامه كإطار تعليمي لفهم الموضوع وربطه بصفحات المقارنات والصناديق والقطاعات ذات الصلة."
    }
  ]
}
